include/scotch.h
include/scotchf.h
lib64/libscotch.so
lib64/libscotch.so.7.0
lib64/libscotch.so.7.0.9
lib64/libscotcherr.so
lib64/libscotcherr.so.7.0
lib64/libscotcherr.so.7.0.9
lib64/libscotcherrexit.so
lib64/libscotcherrexit.so.7.0
lib64/libscotcherrexit.so.7.0.9
lib64/cmake/scotch/SCOTCHConfig.cmake
lib64/cmake/scotch/SCOTCHConfigVersion.cmake
lib64/cmake/scotch/scotchTargets-release.cmake
lib64/cmake/scotch/scotchTargets.cmake
lib64/cmake/scotch/scotcherrTargets-release.cmake
lib64/cmake/scotch/scotcherrTargets.cmake
lib64/cmake/scotch/scotcherrexitTargets-release.cmake
lib64/cmake/scotch/scotcherrexitTargets.cmake
scotchpy/__init__.py
scotchpy/arch.py
scotchpy/archDom.py
scotchpy/common.py
scotchpy/context.py
scotchpy/dgraph.py
scotchpy/exception.py
scotchpy/find_libs.py
scotchpy/geom.py
scotchpy/graph.py
scotchpy/libscotch.so
scotchpy/libscotch.so.7.0
scotchpy/libscotch.so.7.0.9
scotchpy/maporder.py
scotchpy/mesh.py
scotchpy/scotch.h
scotchpy/scotchf.h
scotchpy/scotchpy_err.cpython-313-x86_64-linux-gnu.so
scotchpy/strat.py
scotchpy/data/bump.grf
scotchpy/data/bump_b100000.grf
scotchpy/data/m4x4.grf
scotchpy/data/small_55.msh
scotchpy64-1.0.1.dist-info/METADATA
scotchpy64-1.0.1.dist-info/WHEEL
scotchpy64-1.0.1.dist-info/RECORD
scotchpy64-1.0.1.dist-info/licenses/LICENSE.txt
