Metadata-Version: 2.4
Name: scotchpy64
Version: 1.0.1
Summary: The official Python interface to the Scotch and PT-Scotch graph partitioning libraries
Keywords: graph,partitioning,mapping,reordering,sparse matrix
Author: Pierre PAVIA
Author-Email: Aymen ALI YAHIA <aymenali.aay@gmail.com>, Marc FUENTES <marc.fuentes@inria.fr>, Francois PELLEGRINI <francois.pellegrini@u-bordeaux.fr>
Maintainer-Email: Marc Fuentes <marc.fuentes@inria.fr>
License-Expression: BSD-2-Clause
License-File: LICENSE.txt
Classifier: Intended Audience :: Science/Research
Classifier: Intended Audience :: Developers
Classifier: Programming Language :: C
Classifier: Programming Language :: Python
Classifier: Topic :: Software Development
Classifier: Topic :: Scientific/Engineering
Classifier: Development Status :: 4 - Beta
Classifier: Operating System :: POSIX
Classifier: Programming Language :: Python :: 3
Classifier: Programming Language :: Python :: 3.10
Classifier: Programming Language :: Python :: 3.11
Classifier: Programming Language :: Python :: 3.12
Classifier: Programming Language :: Python :: Implementation :: CPython
Requires-Python: >=3.10
